{
    "robots": [
        {
            "name": "M-6iB",
            "type": "robotic arm",
            "manufacturer": "Fanuc",
            "xacro-generated": true,
            "urdf": [
                "urdf/m6ib.urdf"
            ],
            "variant": null,
            "source-link": "https://github.com/ros-industrial/fanuc/tree/74d7d441311590d3950b03da9a1a86409332c2e8/fanuc_m6ib_support",
            "id": 204
        },
        {
            "name": "M-6iB/6S",
            "type": "robotic arm",
            "manufacturer": "Fanuc",
            "xacro-generated": true,
            "urdf": [
                "urdf/m6ib6s.urdf"
            ],
            "variant": null,
            "source-link": "https://github.com/ros-industrial/fanuc/tree/74d7d441311590d3950b03da9a1a86409332c2e8/fanuc_m6ib_support",
            "id": 205
        }
    ]
}